LeetcodeQuanjieDoocsKaiyuanShequ/README.md
LeetcodeQuanjieDoocsKaiyuanShequ/__init__.py
LeetcodeQuanjieDoocsKaiyuanShequ/__main__.py
LeetcodeQuanjieDoocsKaiyuanShequ/file.epub
LeetcodeQuanjieDoocsKaiyuanShequ/index.html
LeetcodeQuanjieDoocsKaiyuanShequ/css/__init__.py
LeetcodeQuanjieDoocsKaiyuanShequ/css/annotations.css
LeetcodeQuanjieDoocsKaiyuanShequ/css/main.css
LeetcodeQuanjieDoocsKaiyuanShequ/css/normalize.css
LeetcodeQuanjieDoocsKaiyuanShequ/css/popup.css
LeetcodeQuanjieDoocsKaiyuanShequ/font/__init__.py
LeetcodeQuanjieDoocsKaiyuanShequ/font/fontello.eot
LeetcodeQuanjieDoocsKaiyuanShequ/font/fontello.svg
LeetcodeQuanjieDoocsKaiyuanShequ/font/fontello.ttf
LeetcodeQuanjieDoocsKaiyuanShequ/font/fontello.woff
LeetcodeQuanjieDoocsKaiyuanShequ/img/__init__.py
LeetcodeQuanjieDoocsKaiyuanShequ/img/annotator-glyph-sprite.png
LeetcodeQuanjieDoocsKaiyuanShequ/img/annotator-icon-sprite.png
LeetcodeQuanjieDoocsKaiyuanShequ/img/apple-touch-icon.png
LeetcodeQuanjieDoocsKaiyuanShequ/img/cancelfullscreen.png
LeetcodeQuanjieDoocsKaiyuanShequ/img/close.png
LeetcodeQuanjieDoocsKaiyuanShequ/img/fullscreen.png
LeetcodeQuanjieDoocsKaiyuanShequ/img/loader.gif
LeetcodeQuanjieDoocsKaiyuanShequ/img/menu-icon.png
LeetcodeQuanjieDoocsKaiyuanShequ/img/save.png
LeetcodeQuanjieDoocsKaiyuanShequ/img/saved.png
LeetcodeQuanjieDoocsKaiyuanShequ/img/settings-s.png
LeetcodeQuanjieDoocsKaiyuanShequ/img/settings.png
LeetcodeQuanjieDoocsKaiyuanShequ/img/star.png
LeetcodeQuanjieDoocsKaiyuanShequ/js/__init__.py
LeetcodeQuanjieDoocsKaiyuanShequ/js/epub.js
LeetcodeQuanjieDoocsKaiyuanShequ/js/epub.min.js
LeetcodeQuanjieDoocsKaiyuanShequ/js/epub.min.map
LeetcodeQuanjieDoocsKaiyuanShequ/js/hooks.min.js
LeetcodeQuanjieDoocsKaiyuanShequ/js/hooks.min.map
LeetcodeQuanjieDoocsKaiyuanShequ/js/reader.js
LeetcodeQuanjieDoocsKaiyuanShequ/js/reader.js.map
LeetcodeQuanjieDoocsKaiyuanShequ/js/reader.min.js
LeetcodeQuanjieDoocsKaiyuanShequ/js/reader.min.map
LeetcodeQuanjieDoocsKaiyuanShequ/js/hooks/__init__.py
leetcode_quanjie_doocs_kaiyuan_shequ-2024.3.6.0.dist-info/METADATA
leetcode_quanjie_doocs_kaiyuan_shequ-2024.3.6.0.dist-info/WHEEL
leetcode_quanjie_doocs_kaiyuan_shequ-2024.3.6.0.dist-info/entry_points.txt
leetcode_quanjie_doocs_kaiyuan_shequ-2024.3.6.0.dist-info/top_level.txt
leetcode_quanjie_doocs_kaiyuan_shequ-2024.3.6.0.dist-info/RECORD
